slack_blocksmith/__init__.py
slack_blocksmith/blocks.py
slack_blocksmith/composition.py
slack_blocksmith/elements.py
slack_blocksmith/message.py
slack_blocksmith/validators.py
slack_blocksmith-1.1.0.dist-info/METADATA
slack_blocksmith-1.1.0.dist-info/WHEEL
slack_blocksmith-1.1.0.dist-info/RECORD
