Metadata-Version: 2.4
Name: slack-blocksmith
Version: 1.1.0
Summary: A Python package for building Slack Block Kit structures with dedicated classes using builder pattern
Project-URL: Homepage, https://github.com/ppopov212/slack-blocksmith
Project-URL: Repository, https://github.com/ppopov212/slack-blocksmith
Project-URL: Documentation, https://github.com/ppopov212/slack-blocksmith#readme
Project-URL: Issues, https://github.com/ppopov212/slack-blocksmith/issues
Author-email: Peter Popov <ppopov1357@gmail.com>
Maintainer-email: Peter Popov <ppopov1357@gmail.com>
License: MIT
Keywords: api,block-kit,bot,builder,messaging,slack
Classifier: Development Status :: 4 - Beta
Classifier: Intended Audience :: Developers
Classifier: License :: OSI Approved :: MIT License
Classifier: Operating System :: OS Independent
Classifier: Programming Language :: Python :: 3
Classifier: Programming Language :: Python :: 3.8
Classifier: Programming Language :: Python :: 3.9
Classifier: Programming Language :: Python :: 3.10
Classifier: Programming Language :: Python :: 3.11
Classifier: Programming Language :: Python :: 3.12
Classifier: Topic :: Communications :: Chat
Classifier: Topic :: Internet :: WWW/HTTP :: Dynamic Content
Classifier: Topic :: Software Development :: Libraries :: Python Modules
Requires-Python: >=3.8
Requires-Dist: pydantic>=2.0.0
Provides-Extra: dev
Requires-Dist: mypy>=1.0.0; extra == 'dev'
Requires-Dist: pytest-cov>=4.0.0; extra == 'dev'
Requires-Dist: pytest>=7.0.0; extra == 'dev'
Requires-Dist: ruff>=0.1.0; extra == 'dev'
